{
  "spec": {
    "title": "Web Bluetooth",
    "url": "https://webbluetoothcg.github.io/web-bluetooth/"
  },
  "refs": {
    "normative": [
      {
        "name": "BLUETOOTH-ASSIGNED",
        "url": "https://www.bluetooth.com/specifications/assigned-numbers/"
      },
      {
        "name": "BLUETOOTH-SUPPLEMENT6",
        "url": "https://www.bluetooth.org/DocMan/handlers/DownloadDoc.ashx?doc_id=302735"
      },
      {
        "name": "BLUETOOTH42",
        "url": "https://www.bluetooth.org/DocMan/handlers/DownloadDoc.ashx?doc_id=286439"
      },
      {
        "name": "DOM",
        "url": "https://dom.spec.whatwg.org/"
      },
      {
        "name": "ECMAScript",
        "url": "https://tc39.es/ecma262/multipage/"
      },
      {
        "name": "ENCODING",
        "url": "https://encoding.spec.whatwg.org/"
      },
      {
        "name": "FINGERPRINTING-GUIDANCE",
        "url": "https://w3c.github.io/fingerprinting-guidance/"
      },
      {
        "name": "HTML",
        "url": "https://html.spec.whatwg.org/multipage/"
      },
      {
        "name": "INFRA",
        "url": "https://infra.spec.whatwg.org/"
      },
      {
        "name": "PAGE-VISIBILITY",
        "url": "https://www.w3.org/TR/page-visibility/"
      },
      {
        "name": "PERMISSIONS",
        "url": "https://w3c.github.io/permissions/"
      },
      {
        "name": "PERMISSIONS-POLICY-1",
        "url": "https://w3c.github.io/webappsec-permissions-policy/"
      },
      {
        "name": "RFC2119",
        "url": "https://datatracker.ietf.org/doc/html/rfc2119"
      },
      {
        "name": "RFC4122",
        "url": "https://www.rfc-editor.org/rfc/rfc4122"
      },
      {
        "name": "WEBDRIVER-BIDI",
        "url": "https://w3c.github.io/webdriver-bidi/"
      },
      {
        "name": "WEBDRIVER1",
        "url": "https://w3c.github.io/webdriver/"
      },
      {
        "name": "WEBDRIVER2",
        "url": "https://w3c.github.io/webdriver/"
      },
      {
        "name": "WEBHID",
        "url": "https://wicg.github.io/webhid/"
      },
      {
        "name": "WEBIDL",
        "url": "https://webidl.spec.whatwg.org/"
      }
    ],
    "informative": [
      {
        "name": "CSP3",
        "url": "https://w3c.github.io/webappsec-csp/"
      }
    ]
  }
}