{
  "spec": {
    "title": "EPUB 3.3",
    "url": "https://w3c.github.io/epub-specs/epub33/core/"
  },
  "links": {
    "https://www.w3.org/TR/": [],
    "https://www.w3.org/groups/wg/epub": [],
    "https://www.w3.org/Consortium/Patent-Policy/": [
      "def-essential",
      "sec-Disclosure"
    ],
    "https://www.w3.org/groups/wg/epub/ipr": [],
    "https://www.w3.org/2021/Process-20211102/": [],
    "https://www.w3.org/TR/epub-rs-33/": [
      "confreq-zip-rootdir",
      "sec-epub-rs-conf-cmt",
      "confreq-css-rs-fonts",
      "sec-linked-records",
      "sec-scripted-content",
      "confreq-rs-scripted-fxl-support",
      "confreq-rs-scripted-scrolled",
      "note-table-reading-mode",
      "sec-nav",
      "sec-security-privacy",
      "app-epubReadingSystem",
      "sec-property-datatype"
    ],
    "https://www.w3.org/TR/epub-a11y-11/": [],
    "https://www.w3.org/TR/epub-overview-33/": [
      "sec-rendering"
    ],
    "https://www.w3.org/TR/MathML3/": [
      "mixing.elements.annotation.xml"
    ],
    "https://url.spec.whatwg.org/": [
      "concept-url",
      "concept-url-parser",
      "concept-base-url",
      "percent-encode",
      "path-relative-scheme-less-url-string",
      "url-fragment-string",
      "concept-url-serializer",
      "absolute-url-with-fragment-string",
      "relative-url-with-fragment-string",
      "double-dot-path-segment",
      "valid-url-string",
      "absolute-url-string",
      "concept-domain",
      "origin",
      "relative-url-string"
    ],
    "https://html.spec.whatwg.org/": [
      "the-a-element",
      "forms",
      "the-xhtml-syntax",
      "the-link-element",
      "the-track-element",
      "the-video-element",
      "the-source-element",
      "embedded-content",
      "the-img-element",
      "flow-content",
      "the-audio-element",
      "the-picture-element",
      "top-level-browsing-context",
      "the-iframe-element",
      "resolving-urls",
      "the-script-element",
      "the-area-element",
      "embedded-content-2",
      "extensibility-2",
      "the-head-element",
      "microdata",
      "the-base-element",
      "document-base-url",
      "the-rp-element",
      "the-embed-element",
      "the-object-element",
      "the-body-element",
      "svg-0",
      "the-dir-attribute",
      "the-bdo-element",
      "data-block",
      "the-canvas-element",
      "the-nav-element",
      "the-h1,-h2,-h3,-h4,-h5,-and-h6-elements",
      "the-ol-element",
      "the-li-element",
      "the-span-element",
      "phrasing-content",
      "the-hidden-attribute",
      "palpable-content",
      "attr-aria-role",
      "global-attributes",
      "the-div-element",
      "the-html-element",
      "link-type-alternate"
    ],
    "https://datatracker.ietf.org/doc/html/bcp14": [],
    "https://www.w3.org/publishing/epubcheck/": [],
    "https://www.w3.org/publishing/epubcheck/docs/apps-and-tools/": [],
    "https://w3c.github.io/epub-tests/": [
      "pub-cmt-gif",
      "pub-cmt-jpeg",
      "pub-cmt-png",
      "pub-cmt-svg",
      "cnt-svg-support",
      "pub-cmt-webp",
      "pub-cmt-mp3",
      "pub-cmt-mp4",
      "pub-cmt-opus",
      "ocf-url_manifest",
      "ocf-url_relative",
      "ocf-url_link-relative",
      "ocf-url_link-path-absolute",
      "ocf-url_parse-path-absolute",
      "ocf-url_link-leaking-relative",
      "ocf-url_parse-leaking-relative",
      "pkg-dir_creator-rtl",
      "pkg-dir_rtl-root-ltr",
      "pkg-dir_rtl-root-unset",
      "pkg-dir_unset-root-rtl",
      "pkg-dir_unset-root-unset",
      "pkg-dir-auto_root-rtl",
      "pkg-dir-auto_root-unset",
      "pkg-linked-records",
      "pkg-spine-nonlinear",
      "fxl-layout-duplication",
      "fxl-orientation-duplication",
      "fxl-xhtml-icb",
      "pkg-flow-paginated",
      "pkg-flow-scrolled-continuous",
      "pkg-flow-scrolled-doc",
      "css-epub-text-orientation",
      "css-epub-writing-mode",
      "css-epub-text-combine-horizontal",
      "css-epub-hyphens",
      "css-epub-line-break",
      "css-epub-text-align-last",
      "css-epub-word-break",
      "css-epub-text-transform",
      "css-epub-text-emphasis",
      "css-epub-text-underline-position"
    ],
    "https://www.w3.org/TR/SVG/": [
      "ImageElement",
      "ForeignObjectElement",
      "ConformingSVGXMLFragments",
      "ConformingSVGStandAloneFiles",
      "TitleElement",
      "DirectionProperty",
      "PresentationAttributes",
      "ScriptElement",
      "ViewBoxAttribute",
      "SVGFragmentIdentifiers"
    ],
    "https://www.rfc-editor.org/rfc/rfc2397": [],
    "https://www.w3.org/TR/xml-names/": [
      "Conformance",
      "NT-Prefix"
    ],
    "https://www.w3.org/TR/xml/": [
      "dt-doctype",
      "NT-ExternalID",
      "dt-extent",
      "sec-common-syn",
      "sec-lang-tag",
      "dt-pubid",
      "dt-sysid"
    ],
    "https://www.w3.org/TR/epub-multi-rend-11/": [
      "container"
    ],
    "https://www.w3.org/TR/charmod-norm/": [
      "CanonicalFoldNormalizationStep"
    ],
    "https://www.w3.org/TR/international-specs/": [
      "char_truncation"
    ],
    "https://infra.spec.whatwg.org/": [
      "list",
      "list-prepend",
      "string-concatenate",
      "strip-leading-and-trailing-ascii-whitespace",
      "strip-and-collapse-ascii-whitespace"
    ],
    "https://www.w3.org/TR/xmlenc-core1/": [
      "sec-eg-Symmetric-Key"
    ],
    "https://www.w3.org/TR/xmldsig-core/": [
      "sec-EnvelopedSignature"
    ],
    "https://www.w3.org/TR/xmldsig-core1/": [
      "sec-Overview"
    ],
    "https://www.unicode.org/reports/tr9/tr9-44.html": [
      "BD5"
    ],
    "https://www.rfc-editor.org/rfc/rfc5646": [
      "section-2.2.9"
    ],
    "https://dom.spec.whatwg.org/": [
      "concept-child-text-content"
    ],
    "https://www.dublincore.org/specifications/dublin-core/dcmi-terms/": [
      "http://purl.org/dc/elements/1.1/title",
      "http://purl.org/dc/elements/1.1/language",
      "http://purl.org/dc/elements/1.1/contributor",
      "http://purl.org/dc/elements/1.1/creator",
      "http://purl.org/dc/elements/1.1/date",
      "http://purl.org/dc/elements/1.1/subject",
      "http://purl.org/dc/elements/1.1/type"
    ],
    "https://ns.editeur.org/onix/en/5": [],
    "https://doi.org/": [],
    "https://id.loc.gov/vocabulary/relators.html": [],
    "https://www.idpf.org/epub/vocab/package/types": [],
    "https://www.w3.org/publishing/epub32/epub-packages.html": [
      "sec-metadata-elem-identifiers-pid",
      "sec-collection-elem"
    ],
    "https://idpf.org/epub/301/spec/epub-publications-20140626.html": [
      "sec-bindings-elem",
      "spread-portrait",
      "fxl-property-viewport"
    ],
    "https://www.idpf.org/epub/registries/roles": [],
    "https://www.idpf.org/epub/extensions/roles": [],
    "https://www.idpf.org/epub/20/spec/OPF_2.0.1_draft.htm": [
      "Section2.2",
      "Section2.6",
      "Section2.4.1"
    ],
    "https://www.w3.org/TR/json-ld11/": [],
    "https://idpf.org/epub/301/spec/epub-contentdocs-20140626.html": [
      "sec-xhtml-epub-switch",
      "sec-xhtml-epub-trigger"
    ],
    "https://www.w3.org/TR/css-writing-modes-3/": [
      "direction",
      "unicode-bidi",
      "propdef-text-orientation",
      "propdef-writing-mode",
      "text-combine-upright"
    ],
    "https://www.w3.org/TR/CSS2/": [
      "propdef-list-style",
      "propdef-display",
      "containing-block-details",
      "propdef-page-break-before",
      "characters"
    ],
    "https://www.w3.org/TR/epub-ssv-11/": [
      "pagebreak",
      "bodymatter",
      "toc-1"
    ],
    "https://www.w3.org/TR/UAAG20/": [
      "gl-text-config"
    ],
    "https://xkcd.com/927/": [],
    "https://creativecommons.org/licenses/by-nc/2.5/": [],
    "https://www.w3.org/TR/SVG11/": [],
    "https://www.w3.org/TR/SMIL3/": [
      "q22"
    ],
    "https://www.w3.org/TR/epub-tts-10/": [],
    "https://www.daisy.org/guidelines/epub/media-overlays-playback-requirements": [],
    "https://www.w3.org/TR/wcag2/": [],
    "https://fetch.spec.whatwg.org/": [
      "cors-protocol"
    ],
    "https://www.w3.org/TR/CSP2/": [
      "content-security-policy-header-field"
    ],
    "https://www.rfc-editor.org/rfc/rfc7034": [],
    "https://www.w3.org/Consortium/Process/": [
      "adequate-implementation"
    ],
    "https://www.w3.org/TR/dpub-aria/": [],
    "https://www.iso.org/standard/26153.html": [],
    "https://idpf.github.io/epub-registries/authorities/": [],
    "https://idpf.org/epub/30/spec/epub30-publications-20111011.html": [
      "meta-auth",
      "marc21xml-record",
      "mods-record",
      "onix-record",
      "xml-signature",
      "xmp-record"
    ],
    "https://www.idpf.org/epub/vocab/structure/": [
      "pagebreak"
    ],
    "https://www.idpf.org/epub/previews": [],
    "https://www.idpf.org/epub/guides/linked-records/": [],
    "https://www.w3.org/TR/css-text-3/": [
      "hyphens-property",
      "line-break-property",
      "text-align-last-property",
      "word-break-property",
      "text-transform-property"
    ],
    "https://www.w3.org/TR/css-text-decor-3/": [
      "text-emphasis-color-property",
      "text-emphasis-position-property",
      "text-emphasis-style-property",
      "text-underline-position-property"
    ],
    "https://github.com/w3c/epubcheck/tree/master/src/main/resources/com/adobe/epubcheck/schema/30/package-30.nvdl": [],
    "https://github.com/w3c/epubcheck/tree/master/src/main/resources/com/adobe/epubcheck/schema/30/ocf-container-30.nvdl": [],
    "https://github.com/w3c/epubcheck/tree/master/src/main/resources/com/adobe/epubcheck/schema/30/media-overlay-30.nvdl": [],
    "https://www.w3.org/": [],
    "https://www.w3.org/TR/epub-33/": [],
    "https://www.iana.org/assignments/media-types/application/zip": [],
    "https://datatracker.ietf.org/doc/html/rfc4839": [],
    "https://www.idpf.org/doc_library/epub/OCF_2.0.1_draft.doc": [],
    "https://www.w3.org/publishing/epub/epub-spec.html": [],
    "https://github.com/w3c/epub-specs/issues?q=is%3Aissue+is%3Aclosed+label%3AEPUB33+-label%3ASpec-RS+": [],
    "https://github.com/w3c/epub-specs/issues/2118": [],
    "https://github.com/w3c/epub-specs/issues/2134": [],
    "https://github.com/w3c/epub-specs/issues/2066": [],
    "https://github.com/w3c/epub-specs/issues/2071": [],
    "https://github.com/w3c/epub-specs/issues/2093": [],
    "https://github.com/w3c/epub-specs/pull/2060": [],
    "https://github.com/w3c/epub-specs/pull/2070": [],
    "https://github.com/w3c/epub-specs/pull/2025": [],
    "https://github.com/w3c/epub-specs/issues/2076": [],
    "https://github.com/w3c/epub-specs/issues/2024": [],
    "https://github.com/w3c/epub-specs/issues/2045": [],
    "https://github.com/w3c/epub-specs/issues/2039": [],
    "https://github.com/w3c/epub-specs/issues/2036": [],
    "https://github.com/w3c/epub-specs/issues/2030": [],
    "https://github.com/w3c/epub-specs/issues/2031": [],
    "https://github.com/w3c/epub-specs/issues/1986": [],
    "https://github.com/w3c/epub-specs/issues/1871": [],
    "https://github.com/w3c/epub-specs/issues/1872": [],
    "https://github.com/w3c/epub-specs/issues/1875": [],
    "https://github.com/w3c/epub-specs/issues/1876": [],
    "https://www.w3.org/publishing/groups/epub-wg/Meetings/Minutes/2022-01-20-epub": [
      "resolution1"
    ],
    "https://github.com/w3c/epub-specs/issues/1929": [],
    "https://github.com/w3c/epub-specs/issues/1944": [],
    "https://github.com/w3c/epub-specs/issues/1913": [],
    "https://github.com/w3c/epub-specs/issues/1912": [],
    "https://github.com/w3c/epub-specs/issues/1885": [],
    "https://github.com/w3c/epub-specs/issues/1873": [],
    "https://github.com/w3c/epub-specs/issues/181": [],
    "https://github.com/w3c/epub-specs/issues/1374": [],
    "https://github.com/w3c/epub-specs/issues/1888": [],
    "https://github.com/w3c/epub-specs/issues/1681": [],
    "https://github.com/w3c/epub-specs/issues/1857": [],
    "https://github.com/w3c/epub-specs/issues/1763": [],
    "https://github.com/w3c/epub-specs/issues/1761": [],
    "https://github.com/w3c/epub-specs/issues/1745": [],
    "https://github.com/w3c/epub-specs/issues/1602": [],
    "https://github.com/w3c/epub-specs/issues/1726": [],
    "https://github.com/w3c/epub-specs/issues/1732": [],
    "https://github.com/w3c/epub-specs/issues/1687": [],
    "https://github.com/w3c/epub-specs/issues/1699": [],
    "https://github.com/w3c/epub-specs/issues/1690": [],
    "https://github.com/w3c/epub-specs/issues/1688": [],
    "https://github.com/w3c/epub-specs/issues/1631": [],
    "https://github.com/w3c/epub-specs/pull/1648": [],
    "https://github.com/w3c/epub-specs/issues/1323": [],
    "https://github.com/w3c/epub-specs/issues/1303": [],
    "https://github.com/w3c/epub-specs/issues/808": [],
    "https://github.com/w3c/epub-specs/issues/1666": [],
    "https://github.com/w3c/epub-specs/pull/1664": [],
    "https://github.com/w3c/epub-specs/issues/1353": [],
    "https://github.com/w3c/epub-specs/issues/1586": [],
    "https://github.com/w3c/epub-specs/issues/1312": [],
    "https://github.com/w3c/epub-specs/issues/1628": [],
    "https://github.com/w3c/epub-specs/issues/1630": [],
    "https://github.com/w3c/epub-specs/issues/1613": [],
    "https://github.com/w3c/epub-specs/issues/1087": [],
    "https://github.com/w3c/epub-specs/issues/1500": [],
    "https://github.com/w3c/epub-specs/issues/1129": [],
    "https://github.com/w3c/epub-specs/issues/1583": [],
    "https://github.com/w3c/epub-specs/issues/1564": [],
    "https://github.com/w3c/epub-specs/issues/1538": [],
    "https://github.com/w3c/epub-specs/issues/1566": [],
    "https://github.com/w3c/epub-specs/issues/1205": [],
    "https://github.com/w3c/epub-specs/issues/1322": [],
    "https://github.com/w3c/epub-specs/issues/1361": [],
    "https://github.com/w3c/epub-specs/issues/1458": [],
    "https://github.com/w3c/epub-specs/issues/1528": [],
    "https://github.com/w3c/epub-specs/issues/1294": [],
    "https://github.com/w3c/epub-specs/issues/976": [],
    "https://github.com/w3c/epub-specs/issues/1325": [],
    "https://github.com/w3c/epub-specs/issues/1491": [],
    "https://github.com/w3c/epub-specs/issues/1494": [],
    "https://github.com/w3c/epub-specs/issues/1488": [],
    "https://github.com/w3c/epub-specs/issues/1319": [],
    "https://github.com/w3c/epub-specs/issues/1444": [],
    "https://github.com/w3c/epub-specs/issues/1440": [],
    "https://github.com/w3c/epub-specs/issues/1436": [],
    "https://github.com/w3c/epub-specs/issues/1283": [],
    "https://github.com/w3c/epub-specs/issues/1352": [],
    "https://github.com/w3c/epub-specs/issues/1344": [],
    "https://github.com/w3c/epub-specs/issues/1338": [],
    "https://github.com/w3c/epub-specs/issues/645": [],
    "https://www.w3.org/TR/css-device-adapt-1/": [],
    "https://www.w3.org/TR/CSS21/": [],
    "https://www.w3.org/TR/CSS/": [],
    "https://www.w3.org/TR/NOTE-datetime/": [],
    "https://tc39.es/ecma262/multipage/": [],
    "https://nvlpubs.nist.gov/nistpubs/FIPS/NIST.FIPS.180-4.pdf": [],
    "https://www.w3.org/Graphics/GIF/spec-gif89a.txt": [],
    "https://www.w3.org/TR/html-rdfa/": [],
    "https://www.iso.org/iso/catalogue_detail?csnumber=40874": [],
    "https://www.w3.org/Graphics/JPEG/jfif3.pdf": [],
    "https://www.iso.org/standard/22412.html": [],
    "https://www.iso.org/standard/79110.html": [],
    "https://www.iso.org/standard/76383.html": [],
    "https://www.editeur.org/8/ONIX/": [],
    "https://www.microsoft.com/typography/otspec/default.htm": [],
    "https://www.w3.org/TR/PNG/": [],
    "https://www.w3.org/TR/rdfa-core/": [],
    "https://www.rfc-editor.org/rfc/rfc2046": [],
    "https://www.rfc-editor.org/rfc/rfc2119": [],
    "https://www.rfc-editor.org/rfc/rfc4329": [],
    "https://www.rfc-editor.org/rfc/rfc7845": [],
    "https://www.rfc-editor.org/rfc/rfc8089": [],
    "https://www.rfc-editor.org/rfc/rfc8174": [],
    "https://developer.apple.com/fonts/TrueType-Reference-Manual/": [],
    "https://www.unicode.org/reports/tr15/tr15-51.html": [],
    "https://www.unicode.org/versions/latest/": [],
    "https://www.w3.org/TR/wai-aria/": [],
    "https://developers.google.com/speed/webp/docs/riff_container": [],
    "https://developers.google.com/speed/webp/docs/webp_lossless_bitstream_specification": [],
    "https://www.w3.org/TR/WOFF/": [],
    "https://www.w3.org/TR/WOFF2/": [],
    "https://www.w3.org/TR/xinclude/": [],
    "https://www.w3.org/TR/xmlenc-decrypt/": [],
    "https://www.w3.org/TR/xmlschema-2/": [],
    "https://www.iso.org/iso/home/store/catalogue_tc/catalogue_detail.htm?csnumber=57421": [],
    "https://www.pkware.com/documents/casestudies/APPNOTE.TXT": [],
    "https://www.w3.org/TR/audiobooks/": [],
    "https://www.w3.org/TR/css3-mediaqueries/": [],
    "https://www.w3.org/TR/epub-a11y-tech-11/": [],
    "https://www.itu.int/ITU-T/recommendations/rec.aspx?rec=13189": [],
    "https://standards.iso.org/ittf/PubliclyAvailableStandards/c040833_ISO_IEC_19757-3_2006(E).zip": [],
    "https://standards.iso.org/ittf/PubliclyAvailableStandards/c038615_ISO_IEC_19757-4_2006(E).zip": [],
    "https://www.oasis-open.org/committees/download.php/12572/OpenDocument-v1.0-os.pdf": [],
    "https://standards.iso.org/ittf/PubliclyAvailableStandards/c052348_ISO_IEC_19757-2_2008(E).zip": [],
    "https://www.rfc-editor.org/rfc/rfc3986": [],
    "https://www.rfc-editor.org/rfc/rfc4839": [],
    "https://www.rfc-editor.org/rfc/rfc6386": [],
    "https://www.w3.org/TR/WCAG2/": [],
    "https://www.w3.org/TR/webvtt1/": [],
    "https://xhr.spec.whatwg.org/": [],
    "https://www.w3.org/TR/xmlbase/": [],
    "https://www.w3.org/TR/2013/NOTE-xmlsec-rngschema-20130411/": []
  }
}