{
  "spec": {
    "title": "CSS Positioned Layout Module Level 3",
    "url": "https://drafts.csswg.org/css-position/"
  },
  "dfns": [
    {
      "id": "propdef-position",
      "href": "https://drafts.csswg.org/css-position/#propdef-position",
      "linkingText": [
        "position"
      ],
      "localLinkingText": [],
      "type": "property",
      "for": [],
      "access": "public",
      "informative": false
    },
    {
      "id": "positioned-box",
      "href": "https://drafts.csswg.org/css-position/#positioned-box",
      "linkingText": [
        "positioned box",
        "positioned"
      ],
      "localLinkingText": [],
      "type": "dfn",
      "for": [],
      "access": "public",
      "informative": false
    },
    {
      "id": "valdef-position-static",
      "href": "https://drafts.csswg.org/css-position/#valdef-position-static",
      "linkingText": [
        "static"
      ],
      "localLinkingText": [],
      "type": "value",
      "for": [
        "position"
      ],
      "access": "public",
      "informative": false
    },
    {
      "id": "valdef-position-relative",
      "href": "https://drafts.csswg.org/css-position/#valdef-position-relative",
      "linkingText": [
        "relative"
      ],
      "localLinkingText": [],
      "type": "value",
      "for": [
        "position"
      ],
      "access": "public",
      "informative": false
    },
    {
      "id": "valdef-position-sticky",
      "href": "https://drafts.csswg.org/css-position/#valdef-position-sticky",
      "linkingText": [
        "sticky"
      ],
      "localLinkingText": [],
      "type": "value",
      "for": [
        "position"
      ],
      "access": "public",
      "informative": false
    },
    {
      "id": "valdef-position-absolute",
      "href": "https://drafts.csswg.org/css-position/#valdef-position-absolute",
      "linkingText": [
        "absolute"
      ],
      "localLinkingText": [],
      "type": "value",
      "for": [
        "position"
      ],
      "access": "public",
      "informative": false
    },
    {
      "id": "valdef-position-fixed",
      "href": "https://drafts.csswg.org/css-position/#valdef-position-fixed",
      "linkingText": [
        "fixed"
      ],
      "localLinkingText": [],
      "type": "value",
      "for": [
        "position"
      ],
      "access": "public",
      "informative": false
    },
    {
      "id": "relative-position",
      "href": "https://drafts.csswg.org/css-position/#relative-position",
      "linkingText": [
        "relative position",
        "relatively position",
        "relpos"
      ],
      "localLinkingText": [],
      "type": "dfn",
      "for": [],
      "access": "public",
      "informative": false
    },
    {
      "id": "sticky-position",
      "href": "https://drafts.csswg.org/css-position/#sticky-position",
      "linkingText": [
        "sticky position",
        "sticky position",
        "stickypos"
      ],
      "localLinkingText": [],
      "type": "dfn",
      "for": [],
      "access": "public",
      "informative": false
    },
    {
      "id": "sticky-constraint-rectangle",
      "href": "https://drafts.csswg.org/css-position/#sticky-constraint-rectangle",
      "linkingText": [
        "sticky-constraint rectangle"
      ],
      "localLinkingText": [],
      "type": "dfn",
      "for": [],
      "access": "public",
      "informative": false
    },
    {
      "id": "propdef-top",
      "href": "https://drafts.csswg.org/css-position/#propdef-top",
      "linkingText": [
        "top"
      ],
      "localLinkingText": [],
      "type": "property",
      "for": [],
      "access": "public",
      "informative": false
    },
    {
      "id": "propdef-right",
      "href": "https://drafts.csswg.org/css-position/#propdef-right",
      "linkingText": [
        "right"
      ],
      "localLinkingText": [],
      "type": "property",
      "for": [],
      "access": "public",
      "informative": false
    },
    {
      "id": "propdef-bottom",
      "href": "https://drafts.csswg.org/css-position/#propdef-bottom",
      "linkingText": [
        "bottom"
      ],
      "localLinkingText": [],
      "type": "property",
      "for": [],
      "access": "public",
      "informative": false
    },
    {
      "id": "propdef-left",
      "href": "https://drafts.csswg.org/css-position/#propdef-left",
      "linkingText": [
        "left"
      ],
      "localLinkingText": [],
      "type": "property",
      "for": [],
      "access": "public",
      "informative": false
    },
    {
      "id": "valdef-top-length",
      "href": "https://drafts.csswg.org/css-position/#valdef-top-length",
      "linkingText": [
        "<length>"
      ],
      "localLinkingText": [],
      "type": "value",
      "for": [
        "top",
        "right",
        "bottom",
        "left",
        "offset-start",
        "offset-end",
        "offset-before",
        "offset-after"
      ],
      "access": "public",
      "informative": false
    },
    {
      "id": "valdef-top-percentage",
      "href": "https://drafts.csswg.org/css-position/#valdef-top-percentage",
      "linkingText": [
        "<percentage>"
      ],
      "localLinkingText": [],
      "type": "value",
      "for": [
        "top",
        "right",
        "bottom",
        "left",
        "offset-start",
        "offset-end",
        "offset-before",
        "offset-after"
      ],
      "access": "public",
      "informative": false
    },
    {
      "id": "valdef-top-auto",
      "href": "https://drafts.csswg.org/css-position/#valdef-top-auto",
      "linkingText": [
        "auto"
      ],
      "localLinkingText": [],
      "type": "value",
      "for": [
        "top",
        "right",
        "bottom",
        "left",
        "offset-start",
        "offset-end",
        "offset-before",
        "offset-after"
      ],
      "access": "public",
      "informative": false
    },
    {
      "id": "propdef-inset-before",
      "href": "https://drafts.csswg.org/css-position/#propdef-inset-before",
      "linkingText": [
        "inset-before"
      ],
      "localLinkingText": [],
      "type": "property",
      "for": [],
      "access": "public",
      "informative": false
    },
    {
      "id": "propdef-inset-after",
      "href": "https://drafts.csswg.org/css-position/#propdef-inset-after",
      "linkingText": [
        "inset-after"
      ],
      "localLinkingText": [],
      "type": "property",
      "for": [],
      "access": "public",
      "informative": false
    },
    {
      "id": "propdef-inset-start",
      "href": "https://drafts.csswg.org/css-position/#propdef-inset-start",
      "linkingText": [
        "inset-start"
      ],
      "localLinkingText": [],
      "type": "property",
      "for": [],
      "access": "public",
      "informative": false
    },
    {
      "id": "propdef-inset-end",
      "href": "https://drafts.csswg.org/css-position/#propdef-inset-end",
      "linkingText": [
        "inset-end"
      ],
      "localLinkingText": [],
      "type": "property",
      "for": [],
      "access": "public",
      "informative": false
    }
  ]
}