{
  "spec": {
    "title": "Resource Hints",
    "url": "https://w3c.github.io/resource-hints/"
  },
  "headings": [
    {
      "id": "title",
      "level": "1",
      "title": "Resource Hints"
    },
    {
      "id": "table-of-contents",
      "level": "2",
      "title": "Table of Contents"
    },
    {
      "id": "x1-introduction",
      "level": "2",
      "title": "Introduction"
    },
    {
      "id": "x2-resource-hints",
      "level": "2",
      "title": "Resource Hints"
    },
    {
      "id": "x2-1-dns-prefetch",
      "level": "3",
      "title": "DNS Prefetch"
    },
    {
      "id": "x2-2-preconnect",
      "level": "3",
      "title": "Preconnect"
    },
    {
      "id": "x2-3-prefetch",
      "level": "3",
      "title": "Prefetch"
    },
    {
      "id": "x2-4-prerender",
      "level": "3",
      "title": "Prerender"
    },
    {
      "id": "x3-process",
      "level": "2",
      "title": "Process"
    },
    {
      "id": "x3-1-fetching-the-resource-hint-link",
      "level": "3",
      "title": "Fetching the resource hint link"
    },
    {
      "id": "x3-2-load-and-error-events",
      "level": "3",
      "title": "Load and error events"
    },
    {
      "id": "x4-use-cases",
      "level": "2",
      "title": "Use cases"
    },
    {
      "id": "x4-1-dynamic-request-url-preconnect",
      "level": "3",
      "title": "Dynamic request URL (preconnect)"
    },
    {
      "id": "x4-2-anonymizing-redirect-preconnect",
      "level": "3",
      "title": "Anonymizing redirect (preconnect)"
    },
    {
      "id": "x4-3-speculative-resource-prefetching-prefetch",
      "level": "3",
      "title": "Speculative resource prefetching (prefetch)"
    },
    {
      "id": "x4-4-reactive-resource-prefetching-prefetch",
      "level": "3",
      "title": "Reactive resource prefetching (prefetch)"
    },
    {
      "id": "x4-5-prerendering-prerender",
      "level": "3",
      "title": "Prerendering (prerender)"
    },
    {
      "id": "x5-security-and-privacy",
      "level": "2",
      "title": "Security and Privacy"
    },
    {
      "id": "x6-conformance",
      "level": "2",
      "title": "Conformance"
    },
    {
      "id": "x7-iana-considerations",
      "level": "2",
      "title": "IANA Considerations"
    },
    {
      "id": "x7-1-dns-prefetch-link-relation-type",
      "level": "3",
      "title": "dns-prefetch Link Relation Type"
    },
    {
      "id": "x7-2-preconnect-link-relation-type",
      "level": "3",
      "title": "preconnect Link Relation Type"
    },
    {
      "id": "x7-3-prefetch-link-relation-type",
      "level": "3",
      "title": "prefetch Link Relation Type"
    },
    {
      "id": "x7-4-prerender-link-relation-type",
      "level": "3",
      "title": "prerender Link Relation Type"
    },
    {
      "id": "a-acknowledgments",
      "level": "2",
      "title": "A. Acknowledgments"
    },
    {
      "id": "b-references",
      "level": "2",
      "title": "B. References"
    },
    {
      "id": "b-1-normative-references",
      "level": "3",
      "title": "B.1 Normative references"
    }
  ]
}